coeden/__init__.py
coeden/value_tree.py
coeden/specialClasses/__init__.py
coeden/specialClasses/base_node.py
coeden/specialClasses/tree_iterator.py
coeden-0.2.3.dist-info/METADATA
coeden-0.2.3.dist-info/WHEEL
coeden-0.2.3.dist-info/licenses/LICENSE
coeden-0.2.3.dist-info/RECORD
