Metadata-Version: 2.1
Name: coeden
Version: 0.2.3
Summary: Coeden is a idiomatic library to work with trees in python
Project-URL: Homepage, https://github.com/ElGatoNinja/Coeden
Project-URL: Bug Tracker, https://github.com/ElGatoNinja/Coeden/issues
Author-email: JaimeGAlonso <JaimeGAlonso@outlook.com>
License: MIT License
Classifier: Development Status :: 2 - Pre-Alpha
Classifier: License :: OSI Approved :: MIT License
Classifier: Operating System :: OS Independent
Classifier: Programming Language :: Python :: 3
Requires-Python: >=3.10
